tshistory_alias/__init__.py
tshistory_alias/cli.py
tshistory_alias/db.py
tshistory_alias/helpers.py
tshistory_alias/schema.py
tshistory_alias/schema.sql
tshistory_alias/tsio.py
tshistory_alias-0.6.0.dist-info/METADATA
tshistory_alias-0.6.0.dist-info/WHEEL
tshistory_alias-0.6.0.dist-info/entry_points.txt
tshistory_alias-0.6.0.dist-info/top_level.txt
tshistory_alias-0.6.0.dist-info/RECORD
