Metadata-Version: 2.1
Name: tshistory-alias
Version: 0.6.0
Summary: Computed timeseries on top of the `tshistory` package
Home-page: UNKNOWN
Author: Pythonian
Author-email: arnaud.campeas@pythonian.fr, aurelien.campeas@pythonian.fr
License: UNKNOWN
Platform: UNKNOWN
Classifier: Development Status :: 4 - Beta
Classifier: Intended Audience :: Developers
Classifier: License :: OSI Approved :: GNU Lesser General Public License v3 (LGPLv3)
Classifier: Operating System :: OS Independent
Classifier: Programming Language :: Python :: 3
Classifier: Topic :: Database
Classifier: Topic :: Scientific/Engineering
Classifier: Topic :: Software Development :: Version Control
Requires-Dist: tshistory
